gtec_gds/__init__.py
gtec_gds/__version__.py
gtec_gds/g_nautilus.py
gtec_gds/lib/__init__.py
gtec_gds/lib/constants.cp38-win_amd64.pyd
gtec_gds/lib/gtec_gds_wrapper.cp38-win_amd64.pyd
gtec_gds-1.3.0.dist-info/LICENSE
gtec_gds-1.3.0.dist-info/METADATA
gtec_gds-1.3.0.dist-info/WHEEL
gtec_gds-1.3.0.dist-info/top_level.txt
gtec_gds-1.3.0.dist-info/RECORD
