Metadata-Version: 2.1
Name: gtec-gds
Version: 1.3.0
Summary: A GDS API. To be used only as part of g.Pype.
Home-page: https://www.gtec.at
Author: g.tec medical engineering GmbH
Author-email: support@gtec.at
License: g.tec Non-Commercial License (GNCL)
Classifier: Development Status :: 4 - Beta
Classifier: Operating System :: Microsoft :: Windows
Classifier: Programming Language :: Python :: 3
License-File: LICENSE
Requires-Dist: numpy>=1.14.4
Requires-Dist: cffi>=1.16.0
